[
  {
    "type": "MONSTER",
    "abstract": "mon_lizard_abstract",
    "name": { "str": "abstracted lizard" },
    "color": "white",
    "symbol": "L",
    "bodytype": "gator",
    "material": [ "flesh" ],
    "species": [ "REPTILE" ],
    "categories": [ "WILDLIFE" ],
    "default_faction": "animal",
    "volume": "30 L",
    "weight": "40 kg",
    "hp": 40,
    "speed": 75,
    "attack_cost": 75,
    "melee_skill": 2,
    "melee_dice": 1,
    "melee_dice_sides": 4,
    "dodge": 1,
    "armor_bash": 3,
    "armor_cut": 3,
    "armor_stab": 3,
    "armor_bullet": 0,
    "armor_acid": 0,
    "armor_elec": 0,
    "bleed_rate": 0,
    "vision_day": 40,
    "vision_night": 4,
    "aggression": 0,
    "morale": 100,
    "harvest": "mutant_animal_large_noskin" ,
    "//": "TODO: When effects/spells can mess with path settings + flags move smartness to the effect of dedicated coordinatiors",
    "path_settings": { "avoid_sharp": true, "avoid_traps": false, "max_dist": 400 },
    "flags": [ "SEES", "SMELLS", "HEARS", "WARM", "PRIORITIZE_TARGETS", "PATH_AVOID_DANGER_1" ],
    "anger_triggers": [ "HURT", "FRIEND_DIED", "FRIEND_ATTACKED" ],
    "fear_triggers": [ "SOUND", "FIRE" ],
    "special_attacks": [ { "type": "bite", "cooldown": 15 }, [ "GRAB", 10 ] ]
  },
  {
    "id": "mon_lizard_blue",
    "type": "MONSTER",
    "name": { "str": "blue lizard" },
    "copy-from": "mon_lizard_abstract",
	"color": "blue",
    "description": "A large blue lizard of a species you have never seen before the cataclysm. It sniffs around, looking for prey."
  },
  {
    "id": "mon_lizard_white",
    "type": "MONSTER",
    "name": { "str": "white lizard" },
    "copy-from": "mon_lizard_abstract",
    "description": "A large white lizard of a species you have never seen before the cataclysm. It sniffs around, looking for prey.",
    "hp": 50,
    "speed": 75,
    "attack_cost": 80,
    "melee_skill": 3,
    "aggression": 10,
    "special_attacks": [ { "type": "bite", "cooldown": 10 }, [ "GRAB", 10 ] ]
  },
  {
    "id": "mon_lizard_pink",
    "type": "MONSTER",
    "name": { "str": "pink lizard" },
    "copy-from": "mon_lizard_abstract",
	"color": "pink",
    "description": "A large pink lizard of a species you have never seen before the cataclysm. It sniffs around, looking for prey.",
    "hp": 55,
    "speed": 80,
    "attack_cost": 80,
    "melee_skill": 3,
    "melee_dice": 1,
    "melee_dice_sides": 6,
    "aggression": 20,
    "dodge": 2
  },
  {
    "id": "mon_lizard_yellow",
    "type": "MONSTER",
    "name": { "str": "yellow lizard" },
    "copy-from": "mon_lizard_abstract",
	"color": "yellow",
    "description": "A large yellow lizard of a species you have never seen before the cataclysm. It sniffs around, looking for prey.",
    "hp": 55,
    "speed": 90,
    "attack_cost": 90,
    "melee_skill": 3,
    "melee_dice": 1,
    "melee_dice_sides": 8,
    "aggression": 25,
    "dodge": 2
  },
  {
    "id": "mon_lizard_black",
    "type": "MONSTER",
    "name": { "str": "black lizard" },
    "copy-from": "mon_lizard_abstract",
    "description": "A large black lizard of a species you have never seen before the cataclysm. As it sniffs around, looking for prey, you notice that it is blind.",
    "hp": 55,
	"color": "black",
    "speed": 90,
    "attack_cost": 90,
    "melee_skill": 2,
    "melee_dice": 1,
    "melee_dice_sides": 8,
    "dodge": 1,
    "flags": [ "SMELLS", "KEENNOSE", "HEARS", "GOODHEARING", "WARM" ],
    "aggression": 25,
    "vision_day": 2,
    "vision_night": 2
  },
  {
    "id": "mon_lizard_salamander",
    "type": "MONSTER",
    "name": { "str": "alien salamander" },
    "copy-from": "mon_lizard_abstract",
    "description": "You figure this is some sort of salamander, if salamanders were 2 feet long with rows of razor-sharp teeth. It moves swiftly through water like a torpedo.",
    "hp": 55,
	"color": "pink",
    "speed": 90,
    "attack_cost": 90,
    "melee_skill": 3,
    "melee_dice": 1,
    "melee_dice_sides": 8,
    "dodge": 2,
    "flags": [ "SEES", "SMELLS", "HEARS", "WARM", "PRIORITIZE_TARGETS", "SWIMS" ],
    "aggression": 25
  },
  {
    "id": "mon_lizard_cyan",
    "type": "MONSTER",
    "name": { "str": "cyan lizard" },
    "copy-from": "mon_lizard_abstract",
    "description": "An unknown species of cyan lizard. Every so often, it leaps through the air gracefully in search of prey.",
    "hp": 40,
    "speed": 90,
	"color": "cyan",
    "attack_cost": 90,
    "melee_skill": 3,
    "melee_dice": 1,
    "melee_dice_sides": 8,
    "dodge": 4,
    "aggression": 25,
    "special_attacks": [
      { "type": "bite", "cooldown": 15 },
      [ "GRAB", 10 ],
      { "type": "leap", "cooldown": 10, "max_range": 5, "min_consider_range": 2, "max_consider_range": 4 }
    ]
  },
  {
    "id": "mon_lizard_green",
    "type": "MONSTER",
    "name": { "str": "green lizard" },
    "copy-from": "mon_lizard_abstract",
    "description": "An unknown species of green lizard.",
	"color": "light_green",
    "hp": 75,
    "speed": 110,
    "attack_cost": 110,
    "melee_skill": 3,
    "melee_dice": 2,
    "melee_dice_sides": 6,
    "dodge": 4,
    "aggression": 25,
    "vision_day": 30,
    "special_attacks": [ { "type": "bite", "cooldown": 15 }, [ "GRAB", 10 ] ]
  },
  {
    "id": "mon_lizard_red",
    "type": "MONSTER",
    "name": { "str": "red lizard" },
    "copy-from": "mon_lizard_abstract",
    "description": "A huge red lizard of unknown species with snapping jaws of razor-sharp teeth. Despite its apparent bulk, it moves swiftly and nimbly through the undergrowth in search of prey.",
	"color": "red",
    "hp": 60,
    "speed": 100,
    "attack_cost": 100,
    "melee_skill": 3,
    "melee_dice": 3,
    "melee_dice_sides": 12,
    "dodge": 4,
    "aggression": 90,
    "vision_day": 30,
    "special_attacks": [ { "type": "bite", "cooldown": 5 }, [ "GRAB", 5 ] ]
  }
]
